manipuimg/__init__.py
manipuimg/core.py
manipuimg-0.0.2.dist-info/LICENSE
manipuimg-0.0.2.dist-info/METADATA
manipuimg-0.0.2.dist-info/WHEEL
manipuimg-0.0.2.dist-info/top_level.txt
manipuimg-0.0.2.dist-info/RECORD
