Metadata-Version: 2.1
Name: manipuimg
Version: 0.0.2
Summary: A simple image manipulation library
Home-page: https://github.com/WolfTheDeveloper/manipuimg
Author: WolfTheDev
Author-email: wolfthedev@gmail.com
License-File: LICENSE
Requires-Dist: pillow
Requires-Dist: matplotlib
